enopios/__init__.py
enopios/__main__.py
enopios/app.py
enopios-0.2.0.dist-info/entry_points.txt
enopios-0.2.0.dist-info/LICENSE
enopios-0.2.0.dist-info/WHEEL
enopios-0.2.0.dist-info/METADATA
enopios-0.2.0.dist-info/RECORD
