Metadata-Version: 2.1
Name: enopios
Version: 0.2.0
Summary: 
License: Apache-2.0
Author: Simon Biggs
Author-email: simon.biggs@radiotherapy.ai
Requires-Python: >=3.10,<4.0
Classifier: License :: OSI Approved :: Apache Software License
Classifier: Programming Language :: Python :: 3
Classifier: Programming Language :: Python :: 3.10
Requires-Dist: streamlit
